steinlurks/__init__.py
steinlurks/steinjack.py
steinlurks-0.1.0.dist-info/METADATA
steinlurks-0.1.0.dist-info/WHEEL
steinlurks-0.1.0.dist-info/top_level.txt
steinlurks-0.1.0.dist-info/RECORD
